README.txt
setup.py
dalmatian/__init__.py
dalmatian/matrix.py
dalmatian/test.py
dalmatian.egg-info/PKG-INFO
dalmatian.egg-info/SOURCES.txt
dalmatian.egg-info/dependency_links.txt
dalmatian.egg-info/requires.txt
dalmatian.egg-info/top_level.txt