Metadata-Version: 1.1
Name: dalmatian
Version: 0.1.3
Summary: Visualizing a confusion matrix with gradations
Home-page: https://github.com/shoya140/dalmatian
Author: Shoya Ishimaru
Author-email: shoya.ishimaru@gmail.com
License: MIT
Keywords: confusion matrix
Platform: UNKNOWN
Classifier: Programming Language :: Python :: 2.7
Classifier: Intended Audience :: Science/Research
Classifier: License :: OSI Approved :: MIT License
